GRSdriver/__init__.py
GRSdriver/driver_S2_SAFE.py
GRSdriver/driver_landsat_col2.py
GRSdriver/run.py
GRSdriver/utils.py
GRSdriver/visual.py
GRSdriver/rsr/__init__.py
GRSdriver/rsr/landsat_formatting.py
GRSdriver/rsr/data/L4_TM_RSR.xlsx
GRSdriver/rsr/data/L5_TM_RSR.xlsx
GRSdriver/rsr/data/L7_RSR.xlsx
GRSdriver/rsr/data/L8_Ball_BA_RSR.v1.2.xlsx
GRSdriver/rsr/data/L8_TIRS_Relative_Spectral_Responses.BA_.v1.xlsx
GRSdriver/rsr/data/L9_OLI2_Ball_FPM_RSR.v1.0.xlsx
GRSdriver/rsr/data/L9_TIRS2_Relative_Spectral_Responses.BA.v1.0.xlsx
GRSdriver/rsr/data/Sentinel-2_MSI_Spectral_Responses.xlsx
GRSdriver/rsr/data/__init__.py
GRSdriver/rsr/data/rsr_landsat_8_oli.nc
GRSdriver/rsr/data/rsr_landsat_8_oli_tirs.nc
GRSdriver/rsr/data/rsr_landsat_8_tirs.nc
GRSdriver/rsr/data/rsr_landsat_9_oli.nc
GRSdriver/rsr/data/rsr_landsat_9_oli_tirs.nc
GRSdriver/rsr/data/rsr_landsat_9_tirs.nc
docs/requirements.txt
docs/build/html/_static/scripts/bootstrap.js.LICENSE.txt
docs/source/conf.py
GRSdriver-1.0.7.dist-info/LICENSE
GRSdriver-1.0.7.dist-info/METADATA
GRSdriver-1.0.7.dist-info/WHEEL
GRSdriver-1.0.7.dist-info/entry_points.txt
GRSdriver-1.0.7.dist-info/top_level.txt
GRSdriver-1.0.7.dist-info/RECORD
