Metadata-Version: 2.2
Name: GRSdriver
Version: 1.0.7
Summary: Driver for L1C satellite images dedicated to GRS processor
Author-email: Tristan Harmel <tristan.harmel@gmail.com>
License:                                  Apache License
Project-URL: Documentation, https://grsdriver.readthedocs.io
Project-URL: Homepage, https://github.com/Tristanovsk/GRSdriver
Keywords: Sentinel-2,Landsat-8,Landsat-9,driver,EO satellite
Classifier: License :: OSI Approved :: Apache Software License
Classifier: Programming Language :: Python
Classifier: Programming Language :: Python :: 3
Requires-Python: >=3.9
License-File: LICENSE
Requires-Dist: importlib_resources
Requires-Dist: docopt
Requires-Dist: eoreader>=0.21.1
Requires-Dist: xmltodict
Requires-Dist: rasterio
Requires-Dist: netCDF4
Requires-Dist: numba
Requires-Dist: numpy
Requires-Dist: pandas>=2.0.3
Requires-Dist: pyproj
Requires-Dist: pystac
Requires-Dist: rioxarray>=0.15.0
Requires-Dist: geopandas
Requires-Dist: fiona
Requires-Dist: pyyaml
Provides-Extra: dev
Requires-Dist: black; extra == "dev"
Requires-Dist: bumpver; extra == "dev"
Requires-Dist: isort; extra == "dev"
Requires-Dist: pip-tools; extra == "dev"
Requires-Dist: pytest; extra == "dev"
